<?xml version="1.0" encoding="UTF-8"?>
<!DOCTYPE beans PUBLIC "-//SPRING//DTD BEAN//EN" "http://www.springframework.org/dtd/spring-beans.dtd">
<beans>
  <bean class="com.gotop.Generalprocess.service.impl.GeneralprocessService" id="generalProcessService">
  	<property name="generalProcessDAO" ref="generalProcessDAO" />
  	<property name="generalprocessMainDAO" ref="generalprocessMainDAO" />
  	<property name="generalprocessModeloneDAO" ref="generalprocessModeloneDAO" />
  	<property name="generalprocessModeltwoDAO" ref="tGeneralprocessModeltwoDAO" />
  	<property name="tApproveOpninionDAO" ref="tApproveOpninionDAO" />
  	<property name="jbpmService" ref="jbpmService" />
  	<property name="tProcessBusinessService" ref="tProcessBusinessService" />
  </bean>

  
  <bean class="com.gotop.Generalprocess.service.impl.TGeneralprocessMainService" id="tGeneralprocessMainService">
    <property name="tGeneralprocessMainDAO" ref="generalprocessMainDAO" />
  </bean>
  
  <bean class="com.gotop.Generalprocess.service.impl.TGeneralprocessModeloneService" id="generalprocessModeloneService">
    <property name="tGeneralprocessModeloneDAO" ref="generalprocessModeloneDAO" />
  </bean>
  
  <bean class="com.gotop.Generalprocess.service.impl.TGeneralprocessModeltwoService" id="tGeneralprocessModeltwoService">
    <property name="tGeneralprocessModeltwoDAO" ref="tGeneralprocessModeltwoDAO" />
  </bean>
  
  <bean class="com.gotop.Generalprocess.util.SpringContextUtil" id="SpringContextUtil" />
  
</beans>