<?xml version="1.0" encoding="UTF-8"?>
<!DOCTYPE beans PUBLIC "-//SPRING//DTD BEAN//EN" "http://www.springframework.org/dtd/spring-beans.dtd">
<beans>
  <bean class="com.gotop.Generalprocess.dao.impl.GeneralprocessDAO" id="generalProcessDAO">
    <property name="sqlMapClient" ref="sqlMapClient" />
  </bean>

  
  <bean class="com.gotop.Generalprocess.dao.impl.TGeneralprocessMainDAO" id="generalprocessMainDAO">
    <property name="sqlMapClient" ref="sqlMapClient" />
  </bean>
  
  <bean class="com.gotop.Generalprocess.dao.impl.TGeneralprocessModeloneDAO" id="generalprocessModeloneDAO">
    <property name="sqlMapClient" ref="sqlMapClient" />
  </bean>
  
  
  <bean class="com.gotop.Generalprocess.dao.impl.TGeneralprocessModeltwoDAO" id="tGeneralprocessModeltwoDAO">
    <property name="sqlMapClient" ref="sqlMapClient" />
  </bean>
  
  <bean class="com.gotop.Generalprocess.dao.impl.TGeneralprocessModelthreeDAO" id="tGeneralprocessModelthreeDAO">
    <property name="sqlMapClient" ref="sqlMapClient" />
  </bean>
  </beans>